torchtoolbox/__init__.py
torchtoolbox/data/__init__.py
torchtoolbox/data/dataprefetcher.py
torchtoolbox/data/datasets.py
torchtoolbox/data/dynamic_data_provider.py
torchtoolbox/data/lmdb_dataset.py
torchtoolbox/data/sampler.py
torchtoolbox/data/utils.py
torchtoolbox/io/__init__.py
torchtoolbox/io/structured_data_io.py
torchtoolbox/metric/__init__.py
torchtoolbox/metric/feature_verification.py
torchtoolbox/metric/map.py
torchtoolbox/metric/metric.py
torchtoolbox/nn/__init__.py
torchtoolbox/nn/activation.py
torchtoolbox/nn/conv.py
torchtoolbox/nn/functional.py
torchtoolbox/nn/init.py
torchtoolbox/nn/loss.py
torchtoolbox/nn/metric_loss.py
torchtoolbox/nn/modules.py
torchtoolbox/nn/norm.py
torchtoolbox/nn/operators.py
torchtoolbox/nn/sequential.py
torchtoolbox/nn/transformer.py
torchtoolbox/nn/parallel/EncodingDataParallel.py
torchtoolbox/nn/parallel/__init__.py
torchtoolbox/objects/__init__.py
torchtoolbox/objects/bbox.py
torchtoolbox/optimizer/__init__.py
torchtoolbox/optimizer/drop_block_scheduler.py
torchtoolbox/optimizer/lookahead.py
torchtoolbox/optimizer/lr_scheduler.py
torchtoolbox/optimizer/sgd_gc.py
torchtoolbox/tools/__init__.py
torchtoolbox/tools/config_parser.py
torchtoolbox/tools/convert_lmdb.py
torchtoolbox/tools/distribute.py
torchtoolbox/tools/dotdict.py
torchtoolbox/tools/mixup.py
torchtoolbox/tools/registry.py
torchtoolbox/tools/reset_model_setting.py
torchtoolbox/tools/summary.py
torchtoolbox/tools/tensor_transfer.py
torchtoolbox/tools/utils.py
torchtoolbox/transform/__init__.py
torchtoolbox/transform/autoaugment.py
torchtoolbox/transform/dynamic_transform.py
torchtoolbox/transform/functional.py
torchtoolbox/transform/hybrid.py
torchtoolbox/transform/transforms.py
torchtoolbox-0.1.8.2.dist-info/LICENSE
torchtoolbox-0.1.8.2.dist-info/METADATA
torchtoolbox-0.1.8.2.dist-info/WHEEL
torchtoolbox-0.1.8.2.dist-info/top_level.txt
torchtoolbox-0.1.8.2.dist-info/zip-safe
torchtoolbox-0.1.8.2.dist-info/RECORD
