Metadata-Version: 2.1
Name: torchtoolbox
Version: 0.1.8.2
Summary: ToolBox to make using Pytorch much easier.
Home-page: https://github.com/PistonY/torch-toolbox
Author: X.Yang
Author-email: pistonyang@gmail.com
License: BSD 3-Clause
Platform: UNKNOWN
Classifier: Programming Language :: Python :: 3
Requires-Dist: numpy
Requires-Dist: tqdm
Requires-Dist: pyarrow
Requires-Dist: six
Requires-Dist: lmdb
Requires-Dist: scikit-learn
Requires-Dist: scipy
Requires-Dist: opencv-python
Requires-Dist: pyyaml
Requires-Dist: tensorboard
Requires-Dist: prettytable
Requires-Dist: transformers
